{
	"$help": "https://aka.ms/terminal-documentation",
	"$schema": "https://aka.ms/terminal-profiles-schema",
	"actions": [
		{
			"command": {
				"action": "copy",
				"singleLine": false
			},
			"id": "User.copy.644BA8F2"
		},
		{
			"command": "paste",
			"id": "User.paste"
		},
		{
			"command": {
				"action": "splitPane",
				"split": "auto",
				"splitMode": "duplicate"
			},
			"id": "User.splitPane.A6751878"
		},
		{
			"command": "find",
			"id": "User.find"
		}
	],
	"centerOnLaunch": true,
	"copyFormatting": "none",
	"copyOnSelect": false,
	"defaultProfile": "{51855cb2-8cce-5362-8f54-464b92b32386}",
	"initialPosition": ",",
	"keybindings": [
		{
			"id": "User.copy.644BA8F2",
			"keys": "ctrl+c"
		},
		{
			"id": "User.find",
			"keys": "ctrl+shift+f"
		},
		{
			"id": "User.paste",
			"keys": "ctrl+v"
		},
		{
			"id": "User.splitPane.A6751878",
			"keys": "alt+shift+d"
		}
	],
	"launchMode": "default",
	"newTabMenu": [
		{
			"type": "remainingProfiles"
		}
	],
	"profiles": {
		"defaults": {
			"font": {
				"face": "JetBrainsMono Nerd Font"
			}
		},
		"list": [
			{
				"commandline": "%SystemRoot%\\System32\\WindowsPowerShell\\v1.0\\powershell.exe",
				"guid": "{61c54bbd-c2c6-5271-96e7-009a87ff44bf}",
				"hidden": false,
				"name": "Windows PowerShell"
			},
			{
				"commandline": "%SystemRoot%\\System32\\cmd.exe",
				"guid": "{0caa0dad-35be-5f56-a8ff-afceeeaa6101}",
				"hidden": false,
				"name": "\u041a\u043e\u043c\u0430\u043d\u0434\u043d\u0430\u044f \u0441\u0442\u0440\u043e\u043a\u0430"
			},
			{
				"guid": "{b453ae62-4e3d-5e58-b989-0a998ec441b8}",
				"hidden": false,
				"name": "Azure Cloud Shell",
				"source": "Windows.Terminal.Azure"
			},
			{
				"guid": "{574e775e-4f2a-5b96-ac1e-a2962a402336}",
				"hidden": false,
				"name": "PowerShell",
				"source": "Windows.Terminal.PowershellCore"
			},
			{
				"guid": "{24487ec9-130b-587e-8411-65cd7b6ad887}",
				"hidden": false,
				"name": "Developer Command Prompt for VS 2022",
				"source": "Windows.Terminal.VisualStudio"
			},
			{
				"guid": "{d8042822-6aa0-5f73-bcbf-da7e92f8eaf9}",
				"hidden": false,
				"name": "Developer PowerShell for VS 2022",
				"source": "Windows.Terminal.VisualStudio"
			},
			{
				"colorScheme": "Kanagawa",
				"guid": "{51855cb2-8cce-5362-8f54-464b92b32386}",
				"hidden": false,
				"name": "Ubuntu",
				"source": "CanonicalGroupLimited.Ubuntu_79rhkp1fndgsc"
			},
			{
				"guid": "{2c4de342-38b7-51cf-b940-2309a097f518}",
				"hidden": true,
				"name": "Ubuntu",
				"source": "Windows.Terminal.Wsl"
			}
		]
	},
	"schemes": [
		{
			"background": "#1F1F28",
			"black": "#1F1F28",
			"blue": "#658594",
			"brightBlack": "#2A2A37",
			"brightBlue": "#7FB4CA",
			"brightCyan": "#A3D4D5",
			"brightGreen": "#98BB6C",
			"brightPurple": "#D27E99",
			"brightRed": "#FF5D62",
			"brightWhite": "#DCD7BA",
			"brightYellow": "#E6C384",
			"cursorColor": "#DCD7BA",
			"cyan": "#9CABCA",
			"foreground": "#DCD7BA",
			"green": "#76946A",
			"name": "Kanagawa",
			"purple": "#957FB8",
			"red": "#E82424",
			"selectionBackground": "#2A2A37",
			"white": "#DCD7BA",
			"yellow": "#FF9E3B"
		}
	],
	"themes": []
}